safemode/__init__.py
safemode/safemode.py
safemode-1.0.0.dist-info/LICENSE
safemode-1.0.0.dist-info/METADATA
safemode-1.0.0.dist-info/WHEEL
safemode-1.0.0.dist-info/top_level.txt
safemode-1.0.0.dist-info/RECORD
